MANIFEST.in
README.md
setup.py
configmy/__init__.py
configmy/configmy.py
configmy.egg-info/PKG-INFO
configmy.egg-info/SOURCES.txt
configmy.egg-info/dependency_links.txt
configmy.egg-info/top_level.txt
pkg/copr-build.sh
pkg/entry_points.txt
pkg/gen-authors.sh
pkg/gen-readme.sh
pkg/nose.cfg
pkg/package.spec.in
pkg/requirements_full-py-2.6.txt
pkg/requirements_full.txt
pkg/rpmbuild-wrapper.sh
pkg/runtest.sh
pkg/scrutinizer.yml
pkg/test_requirements-py-2.6.txt
pkg/test_requirements.txt
tests/__init__.py